{
  "MSFT": {
    "ticker": "MSFT",
    "current_price": 420.260009765625,
    "mc_median_5y": 63.31178312037507,
    "mc_p10_5y": -20.449947274190762,
    "mc_p90_5y": 220.38973142588864,
    "garch_vol": 29.609849600812126,
    "garch_nu": 8.0,
    "crash_prob_3m": 4.17,
    "signal_action": "Hold",
    "signal_score": -0.073,
    "beta": 1.107,
    "sector": "Technology",
    "all_keys": [
      "ticker",
      "name",
      "sector",
      "current_price",
      "market_cap",
      "cap_tier",
      "beta",
      "pe_ratio",
      "analyst_target",
      "hist_drift",
      "capped_drift",
      "volatility",
      "expected_return",
      "median_return",
      "p05_price",
      "p95_price",
      "prob_loss_5y",
      "avg_max_drawdown",
      "sharpe",
      "mc_median_5y_return",
      "mc_p10_5y_return",
      "mc_p90_5y_return",
      "garch_annual_vol",
      "garch_nu",
      "garch_persistence",
      "ml_crash_prob",
      "tail_risk",
      "prediction_confidence",
      "analyst_targets",
      "recommendations",
      "holders",
      "news",
      "earnings",
      "price_history",
      "momentum_1m",
      "momentum_3m",
      "key_stats",
      "peers",
      "options_calibration",
      "factor_exposure"
    ]
  },
  "GOOGL": {
    "ticker": "GOOGL",
    "current_price": 336.0199890136719,
    "mc_median_5y": 54.92173836889105,
    "mc_p10_5y": -28.92879829742927,
    "mc_p90_5y": 222.72792447214835,
    "garch_vol": 28.942179781460865,
    "garch_nu": 8.0,
    "crash_prob_3m": 4.26,
    "signal_action": "Strong Buy",
    "signal_score": 0.523,
    "beta": 1.128,
    "sector": "Communication Services",
    "all_keys": [
      "ticker",
      "name",
      "sector",
      "current_price",
      "market_cap",
      "cap_tier",
      "beta",
      "pe_ratio",
      "analyst_target",
      "hist_drift",
      "capped_drift",
      "volatility",
      "expected_return",
      "median_return",
      "p05_price",
      "p95_price",
      "prob_loss_5y",
      "avg_max_drawdown",
      "sharpe",
      "mc_median_5y_return",
      "mc_p10_5y_return",
      "mc_p90_5y_return",
      "garch_annual_vol",
      "garch_nu",
      "garch_persistence",
      "ml_crash_prob",
      "tail_risk",
      "prediction_confidence",
      "analyst_targets",
      "recommendations",
      "holders",
      "news",
      "earnings",
      "price_history",
      "momentum_1m",
      "momentum_3m",
      "key_stats",
      "peers",
      "options_calibration",
      "factor_exposure"
    ]
  },
  "META": {
    "ticker": "META",
    "current_price": 676.8699951171875,
    "mc_median_5y": 50.44592632981724,
    "mc_p10_5y": -48.92616805921094,
    "mc_p90_5y": 300.0,
    "garch_vol": 40.50417552381834,
    "garch_nu": 8.0,
    "crash_prob_3m": 5.92,
    "signal_action": "Buy",
    "signal_score": 0.197,
    "beta": 1.309,
    "sector": "Communication Services",
    "all_keys": [
      "ticker",
      "name",
      "sector",
      "current_price",
      "market_cap",
      "cap_tier",
      "beta",
      "pe_ratio",
      "analyst_target",
      "hist_drift",
      "capped_drift",
      "volatility",
      "expected_return",
      "median_return",
      "p05_price",
      "p95_price",
      "prob_loss_5y",
      "avg_max_drawdown",
      "sharpe",
      "mc_median_5y_return",
      "mc_p10_5y_return",
      "mc_p90_5y_return",
      "garch_annual_vol",
      "garch_nu",
      "garch_persistence",
      "ml_crash_prob",
      "tail_risk",
      "prediction_confidence",
      "analyst_targets",
      "recommendations",
      "holders",
      "news",
      "earnings",
      "price_history",
      "momentum_1m",
      "momentum_3m",
      "key_stats",
      "peers",
      "options_calibration",
      "factor_exposure"
    ]
  },
  "ABBV": {
    "ticker": "ABBV",
    "current_price": 208.99000549316406,
    "mc_median_5y": 61.85652783263367,
    "mc_p10_5y": -11.062664266948097,
    "mc_p90_5y": 193.9242852309171,
    "garch_vol": 22.428930900067833,
    "garch_nu": 8.0,
    "crash_prob_3m": 2.15,
    "signal_action": "Buy",
    "signal_score": 0.288,
    "beta": 0.364,
    "sector": "Healthcare",
    "all_keys": [
      "ticker",
      "name",
      "sector",
      "current_price",
      "market_cap",
      "cap_tier",
      "beta",
      "pe_ratio",
      "analyst_target",
      "hist_drift",
      "capped_drift",
      "volatility",
      "expected_return",
      "median_return",
      "p05_price",
      "p95_price",
      "prob_loss_5y",
      "avg_max_drawdown",
      "sharpe",
      "mc_median_5y_return",
      "mc_p10_5y_return",
      "mc_p90_5y_return",
      "garch_annual_vol",
      "garch_nu",
      "garch_persistence",
      "ml_crash_prob",
      "tail_risk",
      "prediction_confidence",
      "analyst_targets",
      "recommendations",
      "holders",
      "news",
      "earnings",
      "price_history",
      "momentum_1m",
      "momentum_3m",
      "key_stats",
      "peers",
      "options_calibration",
      "factor_exposure"
    ]
  },
  "ELF": {
    "ticker": "ELF",
    "current_price": 69.25,
    "mc_median_5y": 22.731876741026102,
    "mc_p10_5y": -78.34049338459073,
    "mc_p90_5y": 300.0,
    "garch_vol": 69.37136491890512,
    "garch_nu": 8.0,
    "crash_prob_3m": 7.99,
    "signal_action": "Hold",
    "signal_score": 0.017,
    "beta": 2.389,
    "sector": "Consumer Defensive",
    "all_keys": [
      "ticker",
      "name",
      "sector",
      "current_price",
      "market_cap",
      "cap_tier",
      "beta",
      "pe_ratio",
      "analyst_target",
      "hist_drift",
      "capped_drift",
      "volatility",
      "expected_return",
      "median_return",
      "p05_price",
      "p95_price",
      "prob_loss_5y",
      "avg_max_drawdown",
      "sharpe",
      "mc_median_5y_return",
      "mc_p10_5y_return",
      "mc_p90_5y_return",
      "garch_annual_vol",
      "garch_nu",
      "garch_persistence",
      "ml_crash_prob",
      "tail_risk",
      "prediction_confidence",
      "analyst_targets",
      "recommendations",
      "holders",
      "news",
      "earnings",
      "price_history",
      "momentum_1m",
      "momentum_3m",
      "key_stats",
      "peers",
      "options_calibration",
      "factor_exposure"
    ]
  },
  "MGM": {
    "ticker": "MGM",
    "current_price": 38.4900016784668,
    "mc_median_5y": -15.55278490756119,
    "mc_p10_5y": -65.90543704260487,
    "mc_p90_5y": 104.05992867500542,
    "garch_vol": 35.801995531968146,
    "garch_nu": 8.0,
    "crash_prob_3m": 5.82,
    "signal_action": "Buy",
    "signal_score": 0.235,
    "beta": 1.351,
    "sector": "Consumer Cyclical",
    "all_keys": [
      "ticker",
      "name",
      "sector",
      "current_price",
      "market_cap",
      "cap_tier",
      "beta",
      "pe_ratio",
      "analyst_target",
      "hist_drift",
      "capped_drift",
      "volatility",
      "expected_return",
      "median_return",
      "p05_price",
      "p95_price",
      "prob_loss_5y",
      "avg_max_drawdown",
      "sharpe",
      "mc_median_5y_return",
      "mc_p10_5y_return",
      "mc_p90_5y_return",
      "garch_annual_vol",
      "garch_nu",
      "garch_persistence",
      "ml_crash_prob",
      "tail_risk",
      "prediction_confidence",
      "analyst_targets",
      "recommendations",
      "holders",
      "news",
      "earnings",
      "price_history",
      "momentum_1m",
      "momentum_3m",
      "key_stats",
      "peers",
      "options_calibration",
      "factor_exposure"
    ]
  },
  "DKNG": {
    "ticker": "DKNG",
    "current_price": 23.739999771118164,
    "mc_median_5y": -29.596095271653,
    "mc_p10_5y": -86.44869744553624,
    "mc_p90_5y": 195.2686905509611,
    "garch_vol": 61.0619694849054,
    "garch_nu": 8.0,
    "crash_prob_3m": 7.99,
    "signal_action": "Sell",
    "signal_score": -0.181,
    "beta": 1.674,
    "sector": "Consumer Cyclical",
    "all_keys": [
      "ticker",
      "name",
      "sector",
      "current_price",
      "market_cap",
      "cap_tier",
      "beta",
      "pe_ratio",
      "analyst_target",
      "hist_drift",
      "capped_drift",
      "volatility",
      "expected_return",
      "median_return",
      "p05_price",
      "p95_price",
      "prob_loss_5y",
      "avg_max_drawdown",
      "sharpe",
      "mc_median_5y_return",
      "mc_p10_5y_return",
      "mc_p90_5y_return",
      "garch_annual_vol",
      "garch_nu",
      "garch_persistence",
      "ml_crash_prob",
      "tail_risk",
      "prediction_confidence",
      "analyst_targets",
      "recommendations",
      "holders",
      "news",
      "earnings",
      "price_history",
      "momentum_1m",
      "momentum_3m",
      "key_stats",
      "peers",
      "options_calibration",
      "factor_exposure"
    ]
  },
  "NEM": {
    "ticker": "NEM",
    "current_price": 113.41000366210938,
    "mc_median_5y": 24.412173547351614,
    "mc_p10_5y": -62.465573893063194,
    "mc_p90_5y": 251.41664055003648,
    "garch_vol": 49.831117643916535,
    "garch_nu": 8.0,
    "crash_prob_3m": 3.01,
    "signal_action": "Strong Buy",
    "signal_score": 0.495,
    "beta": 0.475,
    "sector": "Basic Materials",
    "all_keys": [
      "ticker",
      "name",
      "sector",
      "current_price",
      "market_cap",
      "cap_tier",
      "beta",
      "pe_ratio",
      "analyst_target",
      "hist_drift",
      "capped_drift",
      "volatility",
      "expected_return",
      "median_return",
      "p05_price",
      "p95_price",
      "prob_loss_5y",
      "avg_max_drawdown",
      "sharpe",
      "mc_median_5y_return",
      "mc_p10_5y_return",
      "mc_p90_5y_return",
      "garch_annual_vol",
      "garch_nu",
      "garch_persistence",
      "ml_crash_prob",
      "tail_risk",
      "prediction_confidence",
      "analyst_targets",
      "recommendations",
      "holders",
      "news",
      "earnings",
      "price_history",
      "momentum_1m",
      "momentum_3m",
      "key_stats",
      "peers",
      "options_calibration",
      "factor_exposure"
    ]
  }
}